BrazilClimateFinance/AdaptationKw.py
BrazilClimateFinance/CurrencyManipulation.py
BrazilClimateFinance/Data_set_manipulation.py
BrazilClimateFinance/MitigationKw.py
BrazilClimateFinance/PrintFun.py
BrazilClimateFinance/__init__.py
brazilclimatefinance-0.2.3.dist-info/licenses/LICENSE
brazilclimatefinance-0.2.3.dist-info/METADATA
brazilclimatefinance-0.2.3.dist-info/WHEEL
brazilclimatefinance-0.2.3.dist-info/top_level.txt
brazilclimatefinance-0.2.3.dist-info/RECORD
