Metadata-Version: 2.4
Name: BrazilClimateFinance
Version: 0.2.3
Summary: Package that contains all functions to create the data used in the context of the landscape project
Author-email: Eduardo Minsky <eduardo.minsky@cpiglobal.org>
License: MIT
Project-URL: Homepage, https://github.com/climatepolicydata/Brazil-Climate-Finance-Landscape/BrazilClimateFinance
Requires-Python: >=3.8
License-File: LICENSE
Dynamic: license-file
